contextlog/__init__.py
contextlog-1.1.dist-info/METADATA
contextlog-1.1.dist-info/WHEEL
contextlog-1.1.dist-info/top_level.txt
contextlog-1.1.dist-info/RECORD
